anglicize.py
anglicize-0.0.3.dist-info/AUTHORS.rst
anglicize-0.0.3.dist-info/LICENSE
anglicize-0.0.3.dist-info/METADATA
anglicize-0.0.3.dist-info/WHEEL
anglicize-0.0.3.dist-info/top_level.txt
anglicize-0.0.3.dist-info/RECORD
