Metadata-Version: 2.1
Name: anglicize
Version: 0.0.3
Summary: A simple package to help sort non-English names.
Home-page: https://github.com/rciorba/python-anglicize
Author: Radu Ciorba
Author-email: radu@devrandom.ro
License: BSD-2-Clause
Project-URL: Issue Tracker, https://github.com/rciorba/python-anglicize/issues
Platform: UNKNOWN
Classifier: Development Status :: 5 - Production/Stable
Classifier: Intended Audience :: Developers
Classifier: License :: OSI Approved :: BSD License
Classifier: Operating System :: Unix
Classifier: Operating System :: POSIX
Classifier: Operating System :: Microsoft :: Windows
Classifier: Programming Language :: Python
Classifier: Programming Language :: Python :: 3
Classifier: Programming Language :: Python :: 3.5
Classifier: Programming Language :: Python :: 3.6
Classifier: Programming Language :: Python :: 3.7
Classifier: Programming Language :: Python :: 3.8
Classifier: Programming Language :: Python :: Implementation :: CPython
Classifier: Programming Language :: Python :: Implementation :: PyPy
Classifier: Topic :: Utilities
Requires-Python: >=3.5
